{
  "gamevault-actions": {
    "Type": "ActionSet",
    "Content": {
      "SetName": "GameVaultActions",
      "Actions": [
        {
          "Id": "GetAmazonActions",
          "Title": "Get Amazon store actions",
          "Type": "Init",
          "Command": "./scripts/get-json.py amazon-actions"
        }
      ]
    }
  },
  "gamevault-actions-no-tabs": {
    "Type": "ActionSet",
    "Content": {
      "SetName": "GameVaultActionsNoTabs",
      "Actions": [
        {
          "Id": "GetAmazonActions",
          "Title": "Get Amazon store actions",
          "Type": "Init",
          "Command": "./scripts/get-json.py amazon-actions"
        }
      ]
    }
  },
  "main-menu-actions": {
    "Type": "ActionSet",
    "Content": {
      "SetName": "MainMenu",
      "Actions": [
        {
          "Id": "GetAmazonActions",
          "Title": "Get Amazon store actions",
          "Type": "Init",
          "Command": "./scripts/get-json.py amazon-actions"
        }
      ]
    }
  },
  "gamevault-tabs": {
    "Type": "StoreTabs",
    "Content": {
      "Tabs": [
        { "Title": "Amazon", "Type": "GameGrid", "ActionId": "GetAmazonActions" }
      ]
    }
  },
  "amazon-games-login-actions": {
    "Type": "ActionSet",
    "Content": {
      "SetName": "AmazonGamesLoginActions",
      "Actions": [
        {
          "Id": "Login",
          "Title": "Login",
          "Type": "Login",
          "Command": "./scripts/gamevault.sh Amazon login"
        },
        {
          "Id": "LoginLaunchOptions",
          "Title": "Login",
          "Type": "Login",
          "Command": "./scripts/gamevault.sh Amazon login-launch-options"
        },
        {
          "Id": "Logout",
          "Title": "Logout",
          "Type": "Logout",
          "Command": "./scripts/gamevault.sh Amazon logout"
        },
        {
          "Id": "GetContent",
          "Title": "Status",
          "Type": "Status",
          "Command": "./scripts/gamevault.sh Amazon loginstatus"
        },
        {
          "Id": "GetSetting",
          "Title": "Get settings",
          "Type": "GetSettings",
          "Command": "./scripts/gamevault.sh Amazon getsetting"
        },
        {
          "Id": "SaveSetting",
          "Title": "Set settings",
          "Type": "SaveSettings",
          "Command": "./scripts/gamevault.sh Amazon savesetting"
        }
      ]
    }
  },
  "amazon-game-script-actions": {
    "Type": "ScriptSet",
    "Content": {
      "Actions": [
        {
          "ActionId": "Update",
          "Title": "Update Game",
          "Type": "ScriptAction",
          "InstalledOnly": "True"
        },
        {
          "ActionId": "Verify",
          "Title": "Verify Game",
          "Type": "ScriptAction",
          "InstalledOnly": "True"
        },
        {
          "ActionId": "Repair",
          "Title": "Repair Game",
          "Type": "ScriptAction",
          "InstalledOnly": "True"
        },
        {
          "ActionId": "UmuIdUpdate",
          "Title": "Update UMU Id",
          "Type": "ScriptAction",
          "InstalledOnly": "True"
        },
        {
          "ActionId": "LookupProtonfixes",
          "Title": "Lookup Proton Fixes",
          "Type": "ScriptAction",
          "InstalledOnly": "True"
        },
        {
          "ActionId": "ApplyProtonfixes",
          "Title": "Apply Known Fixes",
          "Type": "ScriptActionConfirm",
          "InstalledOnly": "True"
        }
      ]
    }
  },
  "amazon-script-actions": {
    "Type": "ScriptSet",
    "Content": {
      "Actions": [
        {
          "ActionId": "Refresh",
          "Title": "Refresh Games List",
          "Type": "ScriptAction",
          "InstalledOnly": "False"
        }
      ]
    }
  },
  "amazon-exe-actions": {
    "Type": "ActionSet",
    "Content": {
      "SetName": "AmazonExeActions",
      "Actions": [
        {
          "Id": "RunBinary",
          "Title": "Run executable in game folder",
          "Type": "ScriptAction",
          "Command": "./scripts/gamevault.sh Amazon run-exe"
        },
        {
          "Id": "GetContent",
          "Title": "Get executable list",
          "Type": "Content",
          "Command": "./scripts/gamevault.sh Amazon get-exe-list"
        }
      ]
    }
  },
  "amazon-config-actions": {
    "Type": "ActionSet",
    "Content": {
      "SetName": "AmazonPlatformConfigFileActions",
      "Actions": [
        {
          "Id": "GetContent",
          "Title": "Get the ini files as json",
          "Type": "IniEditor",
          "Command": "./scripts/gamevault.sh Amazon getplatformconfig"
        },
        {
          "Id": "SaveContent",
          "Title": "Save the ini files as json",
          "Type": "IniEditor",
          "Command": "./scripts/gamevault.sh Amazon saveplatformconfig"
        }
      ]
    }
  },
  "amazon-tab-config-actions": {
    "Type": "ActionSet",
    "Content": {
      "SetName": "AmazonTabConfigEditor",
      "Actions": [
        {
          "Id": "GetContent",
          "Title": "Get the ini files as json",
          "Type": "IniEditor",
          "Command": "./scripts/gamevault.sh Amazon gettabconfig"
        },
        {
          "Id": "SaveContent",
          "Title": "Save the ini files as json",
          "Type": "IniEditor",
          "Command": "./scripts/gamevault.sh Amazon savetabconfig"
        }
      ]
    }
  },
  "amazon-actions": {
    "Type": "ActionSet",
    "Content": {
      "SetName": "AmazonActions",
      "Actions": [
        {
          "Id": "GetContent",
          "Title": "Get Amazon games list",
          "Type": "GameGrid",
          "Command": "./scripts/gamevault.sh Amazon getgames"
        },
        {
          "Id": "CheckUpdate",
          "Title": "Check for update",
          "Type": "CheckUpdate",
          "Command": "./scripts/gamevault.sh Amazon checkupdate"
        },
        {
          "Id": "GetGameSize",
          "Title": "Get game size",
          "Type": "GameSize",
          "Command": "./scripts/gamevault.sh Amazon getgamesize"
        },
        {
          "Id": "GetDetails",
          "Title": "Get game details",
          "Type": "GameDetails",
          "Command": "./scripts/gamevault.sh Amazon getgamedetails"
        },
        {
          "Id": "GetJsonImages",
          "Title": "Get game images as json",
          "Type": "GameImages",
          "Command": "./scripts/gamevault.sh Amazon getjsonimages"
        },
        {
          "Id": "Install",
          "Title": "Install game",
          "Type": "Install",
          "Command": "./scripts/gamevault.sh Amazon install"
        },
        {
          "Id": "Download",
          "Title": "Download game",
          "Type": "Download",
          "Command": "./scripts/gamevault.sh Amazon download"
        },
        {
          "Id": "Update",
          "Title": "Update game",
          "Type": "Update",
          "Command": "./scripts/gamevault.sh Amazon update"
        },
        {
          "Id": "Repair",
          "Title": "Repair game",
          "Type": "Update",
          "Command": "./scripts/gamevault.sh Amazon repair"
        },
        {
          "Id": "Verify",
          "Title": "Verify game",
          "Type": "Verify",
          "Command": "./scripts/gamevault.sh Amazon verify"
        },
        {
          "Id": "Uninstall",
          "Title": "Uninstall game",
          "Type": "Uninstall",
          "Command": "./scripts/gamevault.sh Amazon uninstall"
        },
        {
          "Id": "GetProgress",
          "Title": "Get install progress",
          "Type": "GetProgress",
          "Command": "./scripts/gamevault.sh Amazon getprogress"
        },
        {
          "Id": "CancelInstall",
          "Title": "Cancel install",
          "Type": "CancelInstall",
          "Command": "./scripts/gamevault.sh Amazon cancelinstall"
        },
        {
          "Id": "GetLoginActions",
          "Title": "Get login status",
          "Type": "Init",
          "Command": "./scripts/get-json.py amazon-games-login-actions"
        },
        {
          "Id": "GetLaunchOptions",
          "Title": "Get launch options",
          "Type": "GetLaunchOptions",
          "Command": "./scripts/gamevault.sh Amazon getlaunchoptions"
        },
        {
          "Id": "GetExeActions",
          "Title": "Get executable action set to run exe's in game dir",
          "Type": "Init",
          "Command": "./scripts/get-json.py amazon-exe-actions"
        },
        {
          "Id": "GetGameScriptActions",
          "Title": "",
          "Type": "ScriptActions",
          "Command": "./scripts/get-json.py amazon-game-script-actions"
        },
        {
          "Id": "GetScriptActions",
          "Title": "",
          "Type": "ScriptActions",
          "Command": "./scripts/get-json.py amazon-script-actions"
        },
        {
          "Id": "GetPlatformConfigFileActions",
          "Title": "Get config file actions",
          "Type": "Init",
          "Command": "./scripts/get-json.py amazon-config-actions"
        },
        {
          "Id": "GetTabConfigActions",
          "Title": "Get Amazon tab config file actions",
          "Type": "Init",
          "Command": "./scripts/get-json.py amazon-tab-config-actions"
        },
        {
          "Id": "Refresh",
          "Title": "Refresh Games List",
          "Type": "Refresh",
          "Command": "./scripts/gamevault.sh Amazon refresh"
        },
        {
          "Id": "UmuIdUpdate",
          "Title": "Update UMU Id",
          "Type": "Executable",
          "Command": "./scripts/gamevault.sh Amazon update-umu-id"
        },
        {
          "Id": "LookupProtonfixes",
          "Title": "Lookup proton fixes",
          "Type": "Executable",
          "Command": "./scripts/gamevault.sh Amazon lookup-protonfixes"
        },
        {
          "Id": "ApplyProtonfixes",
          "Title": "Apply proton fixes",
          "Type": "Executable",
          "Command": "./scripts/gamevault.sh Amazon apply-protonfixes"
        }
      ]
    }
  }
}
